tink-1.13.1.dist-info/RECORD
tink-1.13.1.dist-info/WHEEL
tink-1.13.1.dist-info/top_level.txt
tink-1.13.1.dist-info/METADATA
tink-1.13.1.dist-info/licenses/LICENSE
tink/secret_key_access_import_test.py
tink/secret_key_access.py
tink/tink_config.py
tink/_json_proto_keyset_format.py
tink/_monitoring.py
tink/cleartext_keyset_handle.py
tink/_proto_keyset_format.py
tink/_keyset_writer_test.py
tink/_secret_key_access.py
tink/_keyset_handle.py
tink/_keyset_handle_test.py
tink/_insecure_keyset_handle_test.py
tink/secret_key_access_test.py
tink/_json_proto_keyset_format_test.py
tink/__init__.py
tink/_kms_clients.py
tink/_insecure_keyset_handle.py
tink/_keyset_reader_test.py
tink/cleartext_keyset_handle_test.py
tink/_keyset_writer.py
tink/tink_config_test.py
tink/_proto_keyset_format_test.py
tink/_kms_clients_test.py
tink/_keyset_reader.py
tink/jwt/_jwt_signature_wrappers.py
tink/jwt/_raw_jwt_test.py
tink/jwt/_jwt_validator_test.py
tink/jwt/_jwt_signature_key_manager_test.py
tink/jwt/_jwt_error.py
tink/jwt/_jwt_public_key_verify.py
tink/jwt/_jwk_set_converter.py
tink/jwt/_jwt_mac.py
tink/jwt/_json_util_test.py
tink/jwt/__init__.py
tink/jwt/_jwt_validator.py
tink/jwt/_jwt_hmac_key_manager.py
tink/jwt/_jwt_mac_wrapper.py
tink/jwt/_jwt_key_templates.py
tink/jwt/_jwt_hmac_key_manager_test.py
tink/jwt/_jwt_signature_key_manager.py
tink/jwt/_verified_jwt.py
tink/jwt/_jwt_key_templates_test.py
tink/jwt/_verified_jwt_test.py
tink/jwt/_jwt_mac_wrapper_test.py
tink/jwt/_jwt_public_key_sign.py
tink/jwt/_jwt_format.py
tink/jwt/_jwt_format_test.py
tink/jwt/_json_util.py
tink/jwt/_jwt_signature_wrappers_test.py
tink/jwt/_raw_jwt.py
tink/jwt/_jwk_set_converter_test.py
tink/aead/_aead_key_manager.py
tink/aead/_aead_wrapper_test.py
tink/aead/_aead_key_templates_test.py
tink/aead/__init__.py
tink/aead/_aead_key_templates.py
tink/aead/_kms_aead_key_manager.py
tink/aead/_kms_envelope_aead_test.py
tink/aead/_kms_aead_key_manager_test.py
tink/aead/_kms_envelope_aead.py
tink/aead/_aead_key_manager_test.py
tink/aead/_aead.py
tink/aead/_aead_wrapper.py
tink/prf/_prf_key_manager_test.py
