Metadata-Version: 2.4
Name: tink
Version: 1.13.1
Summary: A multi-language, cross-platform library that provides cryptographic APIs that are secure, easy to use correctly, and hard(er) to misuse.
Home-page: https://github.com/tink-crypto/tink-py
Author: Tink Developers
Author-email: tink-users@googlegroups.com
License: Apache 2.0
Keywords: tink cryptography
Classifier: Programming Language :: Python
Classifier: Programming Language :: Python :: 3
Classifier: Programming Language :: Python :: 3.9
Classifier: Programming Language :: Python :: 3.10
Classifier: Programming Language :: Python :: 3.11
Classifier: Programming Language :: Python :: 3.12
Classifier: Programming Language :: Python :: 3.13
Classifier: Topic :: Software Development :: Libraries
Requires-Python: >=3.9
License-File: LICENSE
Requires-Dist: absl-py>=2.1.0
Requires-Dist: protobuf>=5.29.5
Requires-Dist: bazel-runfiles>=1.3.0
Provides-Extra: gcpkms
Requires-Dist: google-auth>=2.38.0; extra == "gcpkms"
Requires-Dist: google-api-core>=2.24.2; extra == "gcpkms"
Requires-Dist: google-cloud-kms>=3.4.1; extra == "gcpkms"
Provides-Extra: awskms
Requires-Dist: boto3>=1.37.32; extra == "awskms"
Provides-Extra: hcvault
Requires-Dist: hvac>=2.3.0; extra == "hcvault"
Provides-Extra: all
Requires-Dist: google-auth>=2.38.0; extra == "all"
Requires-Dist: google-api-core>=2.24.2; extra == "all"
Requires-Dist: google-cloud-kms>=3.4.1; extra == "all"
Requires-Dist: boto3>=1.37.32; extra == "all"
Requires-Dist: hvac>=2.3.0; extra == "all"
Dynamic: author
Dynamic: author-email
Dynamic: classifier
Dynamic: description
Dynamic: description-content-type
Dynamic: home-page
Dynamic: keywords
Dynamic: license
Dynamic: license-file
Dynamic: provides-extra
Dynamic: requires-dist
Dynamic: requires-python
Dynamic: summary
